metaclean/__init__.py
metaclean/__main__.py
metaclean/assets/icon128.png
metaclean/assets/icon256.png
metaclean/assets/icon512.png
metaclean/core/exiftool.py
metaclean/core/gui.py
metaclean/core/options.py
metaclean/core/process.py
metaclean/data/options.json
metaclean_gui-0.2.1.dist-info/licenses/LICENSE
metaclean_gui-0.2.1.dist-info/METADATA
metaclean_gui-0.2.1.dist-info/WHEEL
metaclean_gui-0.2.1.dist-info/entry_points.txt
metaclean_gui-0.2.1.dist-info/top_level.txt
metaclean_gui-0.2.1.dist-info/RECORD
