Metadata-Version: 2.4
Name: metaclean-gui
Version: 0.2.1
Summary: App to clean metadata from multiple images
Author-email: simon0302010 <simon0302010@gmail.com>
License:                     GNU GENERAL PUBLIC LICENSE
Project-URL: Homepage, https://github.com/simon0302010/metaclean
Classifier: Operating System :: POSIX :: Linux
Classifier: Operating System :: Microsoft :: Windows
Requires-Python: <3.14,>=3.8
License-File: LICENSE
Requires-Dist: PyQt5
Provides-Extra: dev
Requires-Dist: build; extra == "dev"
Requires-Dist: twine; extra == "dev"
Requires-Dist: ruff; extra == "dev"
Dynamic: license-file
